sphinx_tabs_selector/__init__.py
sphinx_tabs_selector/selector.py
sphinx_tabs_selector/static/selector.css
sphinx_tabs_selector/static/tabs.css
sphinx_tabs_selector/static/tabs.js
sphinx_tabs_selector-1.0.12.dist-info/licenses/LICENSE
sphinx_tabs_selector-1.0.12.dist-info/METADATA
sphinx_tabs_selector-1.0.12.dist-info/WHEEL
sphinx_tabs_selector-1.0.12.dist-info/top_level.txt
sphinx_tabs_selector-1.0.12.dist-info/RECORD
