Metadata-Version: 2.4
Name: sphinx-tabs-selector
Version: 1.0.12
Summary: It is used to extract the specified tabs content from the RST (reStructuredText) document.
Author-email: TerraJuly <caijie_hui@163.com>
Maintainer-email: TerraJuly <caijie_hui@163.com>
Project-URL: Homepage, https://github.com/TerraJuly/sphinx_tabs_selector
Classifier: Development Status :: 3 - Alpha
Classifier: Intended Audience :: Developers
Classifier: Topic :: Software Development :: Build Tools
Classifier: License :: OSI Approved :: MIT License
Classifier: Programming Language :: Python :: 3
Classifier: Programming Language :: Python :: 3.6
Classifier: Programming Language :: Python :: 3.7
Classifier: Programming Language :: Python :: 3.8
Classifier: Programming Language :: Python :: 3.9
Classifier: Programming Language :: Python :: 3.10
Classifier: Programming Language :: Python :: 3.11
Classifier: Programming Language :: Python :: 3.12
Classifier: Programming Language :: Python :: 3.13
License-File: LICENSE
Dynamic: license-file
